pyfb_did/__init__.py
pyfb_did/admin.py
pyfb_did/api.py
pyfb_did/apps.py
pyfb_did/forms.py
pyfb_did/models.py
pyfb_did/serializers.py
pyfb_did/sql_config.py
pyfb_did/urls.py
pyfb_did/views.py
pyfb_did/migrations/0001_initial.py
pyfb_did/migrations/0002_auto_20181221_1626.py
pyfb_did/migrations/0003_auto_20181221_1627.py
pyfb_did/migrations/0004_auto_20190130_1838.py
pyfb_did/migrations/0005_auto_20190523_1742.py
pyfb_did/migrations/__init__.py
pyfb_did/static/css/pyfb_did.css
pyfb_did/static/js/pyfb_did.js
pyfb_did/templates/pyfb_did/did_detail.html
pyfb_did/templates/pyfb_did/did_form.html
pyfb_did/templates/pyfb_did/did_list.html
pyfb_did/templates/pyfb_did/routesdid_detail.html
pyfb_did/templates/pyfb_did/routesdid_form.html
pyfb_did/templates/pyfb_did/routesdid_list.html
pyfb_did-1.0.3.dist-info/DESCRIPTION.rst
pyfb_did-1.0.3.dist-info/METADATA
pyfb_did-1.0.3.dist-info/RECORD
pyfb_did-1.0.3.dist-info/WHEEL
pyfb_did-1.0.3.dist-info/metadata.json
pyfb_did-1.0.3.dist-info/top_level.txt
