Metadata-Version: 2.0
Name: pyfb-did
Version: 1.0.3
Summary: Your project description goes here
Home-page: https://www.pyfreebilling.com
Author: Mathias WOLFF
Author-email: mathias@celea.org
License: MIT
Keywords: pyfb-did
Platform: UNKNOWN
Classifier: Development Status :: 5 - Production/Stable
Classifier: Framework :: Django :: 2.2
Classifier: Intended Audience :: Developers
Classifier: License :: OSI Approved :: MIT License
Classifier: Natural Language :: English
Classifier: Programming Language :: Python :: 3.5
Classifier: Programming Language :: Python :: 3.6
Requires-Dist: django-model-utils (>=2.0)
Requires-Dist: djangorestframework (>=3.7.7)
Requires-Dist: django-crispy-forms (>=1.7.0)
Requires-Dist: pyfb-endpoint (>=0.9.0)
Requires-Dist: pyfb-company (>=0.9.0)
Requires-Dist: django-migrate-sql-deux
